{
  "id": 31000,
  "name": "Vector Legal",
  "slug": "vector-legal",
  "former_names": [
    "Cadence",
    "Raise"
  ],
  "small_logo_thumb_url": "https://bookface-images.s3.amazonaws.com/small_logos/24fe2cfdacb0c9b085052b0bee9ce77035a7373e.png",
  "website": "https://vectorlegal.com",
  "all_locations": "San Francisco, CA, USA",
  "long_description": "A modern solution for Startup legal: Vector Legal is a hybrid AI law firm + legal tech platform. Our customers benefit from state of the art software for their legal operations + an experienced lawyer-in-the-loop. \r\n\r\nServices: fundraise & priced rounds | customer contracts | team growth & equity | AI draft & review | agentic data room | e-signatures | contract intelligence | legal health checks | mergers & acquisitions | co-founder separations | company formation.",
  "one_liner": "AI Law Firm + Legal Tech Platform for Startups",
  "team_size": 3,
  "industry": "B2B",
  "subindustry": "B2B -> Legal",
  "launched_at": 1771526564,
  "tags": [
    "Legal",
    "LegalTech",
    "Operations",
    "AI Assistant"
  ],
  "tags_highlighted": [],
  "top_company": false,
  "isHiring": false,
  "nonprofit": false,
  "batch": "Winter 2026",
  "status": "Active",
  "industries": [
    "B2B",
    "Legal"
  ],
  "regions": [
    "United States of America",
    "America / Canada"
  ],
  "stage": "Early",
  "app_video_public": false,
  "demo_day_video_public": false,
  "app_answers": null,
  "question_answers": false,
  "url": "https://www.ycombinator.com/companies/vector-legal",
  "api": "https://yc-oss.github.io/api/batches/winter-2026/vector-legal.json"
}
